{"0":{"id":0,"name":"Leannon, Gerhold and Brekke","bs":"viral target web-readiness"},"1":{"id":1,"name":"Hane - Cartwright","bs":"ubiquitous unleash niches"},"2":{"id":2,"name":"Homenick - Leannon","bs":"holistic deploy schemas"},"3":{"id":3,"name":"Cartwright Group","bs":"global cultivate vortals"},"4":{"id":4,"name":"Schuppe, Lynch and Dickinson","bs":"e-business exploit relationships"},"5":{"id":5,"name":"Leuschke Group","bs":"turn-key recontextualize portals"},"6":{"id":6,"name":"Stroman Group","bs":"bricks-and-clicks engage relationships"},"7":{"id":7,"name":"Hickle, Kulas and Monahan","bs":"next-generation brand functionalities"},"8":{"id":8,"name":"Towne and Sons","bs":"web-enabled empower networks"},"9":{"id":9,"name":"Romaguera - Predovic","bs":"transparent empower web-readiness"},"10":{"id":10,"name":"Murray, Cole and Heathcote","bs":"transparent synergize schemas"},"11":{"id":11,"name":"Wunsch LLC","bs":"turn-key repurpose markets"},"12":{"id":12,"name":"Wolf LLC","bs":"24/365 transition schemas"},"13":{"id":13,"name":"Greenholt and Sons","bs":"best-of-breed architect supply-chains"},"14":{"id":14,"name":"Runte LLC","bs":"magnetic orchestrate e-tailers"},"15":{"id":15,"name":"Harvey Inc","bs":"seamless matrix architectures"},"16":{"id":16,"name":"Bernhard Inc","bs":"leading-edge enhance partnerships"},"17":{"id":17,"name":"Bashirian, Muller and Wiza","bs":"out-of-the-box deploy eyeballs"},"18":{"id":18,"name":"Ward - Cronin","bs":"impactful reinvent partnerships"},"19":{"id":19,"name":"Marquardt - Tillman","bs":"turn-key scale solutions"},"20":{"id":20,"name":"Reichert - Larkin","bs":"customized extend portals"},"21":{"id":21,"name":"Mosciski, West and Welch","bs":"distributed cultivate schemas"},"22":{"id":22,"name":"Kovacek - Buckridge","bs":"clicks-and-mortar drive interfaces"},"23":{"id":23,"name":"Deckow LLC","bs":"e-business monetize models"},"24":{"id":24,"name":"Schumm LLC","bs":"magnetic transform schemas"},"25":{"id":25,"name":"Douglas - Rolfson","bs":"bricks-and-clicks grow infomediaries"},"26":{"id":26,"name":"Gorczany and Sons","bs":"killer mesh functionalities"},"27":{"id":27,"name":"Schumm, Mohr and Fadel","bs":"viral transform paradigms"},"28":{"id":28,"name":"Wiza LLC","bs":"mission-critical incubate e-services"},"29":{"id":29,"name":"Ryan, Ferry and Bauch","bs":"holistic evolve paradigms"},"30":{"id":30,"name":"Treutel Group","bs":"sticky optimize architectures"},"31":{"id":31,"name":"Hermann, D'Amore and Kuphal","bs":"distributed generate e-commerce"},"32":{"id":32,"name":"Marvin, Kilback and Crooks","bs":"visionary grow e-tailers"},"33":{"id":33,"name":"Weissnat, Miller and Runolfsdottir","bs":"sexy reinvent e-services"},"34":{"id":34,"name":"Emmerich, Ullrich and Howell","bs":"vertical facilitate channels"},"35":{"id":35,"name":"Collins, Kessler and Stehr","bs":"clicks-and-mortar synthesize e-markets"},"36":{"id":36,"name":"Heathcote Inc","bs":"intuitive repurpose e-tailers"},"37":{"id":37,"name":"Torp, Stroman and Hills","bs":"value-added benchmark vortals"},"38":{"id":38,"name":"Jerde, Becker and Champlin","bs":"out-of-the-box disintermediate web-readiness"},"39":{"id":39,"name":"Waelchi - Cruickshank","bs":"compelling facilitate eyeballs"},"40":{"id":40,"name":"White LLC","bs":"end-to-end morph portals"},"41":{"id":41,"name":"Watsica and Sons","bs":"customized unleash e-commerce"},"42":{"id":42,"name":"Cremin, Reinger and Dickens","bs":"B2B implement models"},"43":{"id":43,"name":"Rempel Group","bs":"enterprise whiteboard mindshare"},"44":{"id":44,"name":"Leffler - Schulist","bs":"magnetic integrate interfaces"},"45":{"id":45,"name":"Crooks and Sons","bs":"vertical brand architectures"},"46":{"id":46,"name":"Koch Group","bs":"one-to-one embrace networks"},"47":{"id":47,"name":"Aufderhar, Gleason and Hettinger","bs":"back-end synergize mindshare"},"48":{"id":48,"name":"Hegmann Inc","bs":"front-end streamline relationships"},"49":{"id":49,"name":"Hauck Group","bs":"visionary utilize content"},"50":{"id":50,"name":"Corwin - Brown","bs":"synergistic matrix web-readiness"},"51":{"id":51,"name":"Ryan Group","bs":"seamless extend e-business"},"52":{"id":52,"name":"Turner and Sons","bs":"seamless cultivate models"},"53":{"id":53,"name":"Beahan, Schumm and Casper","bs":"value-added redefine schemas"},"54":{"id":54,"name":"Medhurst LLC","bs":"intuitive orchestrate e-services"},"55":{"id":55,"name":"Koelpin LLC","bs":"killer engage web-readiness"},"56":{"id":56,"name":"Emmerich - Harris","bs":"value-added innovate vortals"},"57":{"id":57,"name":"Will LLC","bs":"sticky optimize deliverables"},"58":{"id":58,"name":"Hackett - Dibbert","bs":"impactful target content"},"59":{"id":59,"name":"Berge and Sons","bs":"open-source enable metrics"},"60":{"id":60,"name":"Trantow, Nolan and Johnson","bs":"wireless optimize users"},"61":{"id":61,"name":"Cassin, O'Hara and Zemlak","bs":"real-time utilize applications"},"62":{"id":62,"name":"Nitzsche, Weimann and Ward","bs":"cross-media innovate systems"},"63":{"id":63,"name":"Schumm - Bartoletti","bs":"plug-and-play productize infrastructures"},"64":{"id":64,"name":"Price - Becker","bs":"clicks-and-mortar revolutionize schemas"},"65":{"id":65,"name":"Rosenbaum Inc","bs":"extensible incentivize communities"},"66":{"id":66,"name":"Leffler, Armstrong and Dooley","bs":"front-end embrace applications"},"67":{"id":67,"name":"Doyle LLC","bs":"next-generation whiteboard communities"},"68":{"id":68,"name":"Okuneva, Hartmann and Spencer","bs":"sexy facilitate systems"},"69":{"id":69,"name":"Harvey and Sons","bs":"wireless orchestrate interfaces"},"70":{"id":70,"name":"Lynch, Wuckert and Aufderhar","bs":"sexy deploy e-business"},"71":{"id":71,"name":"Krajcik and Sons","bs":"interactive utilize mindshare"},"72":{"id":72,"name":"Boyle, Goyette and West","bs":"compelling repurpose interfaces"},"73":{"id":73,"name":"Feeney, Spencer and Schulist","bs":"24/365 repurpose infrastructures"},"74":{"id":74,"name":"Batz and Sons","bs":"wireless streamline relationships"},"75":{"id":75,"name":"Collins LLC","bs":"B2C matrix synergies"},"76":{"id":76,"name":"Russel - Spencer","bs":"back-end morph vortals"},"77":{"id":77,"name":"Wisozk Group","bs":"web-enabled repurpose communities"},"78":{"id":78,"name":"Balistreri and Sons","bs":"24/365 innovate deliverables"},"79":{"id":79,"name":"Schimmel, Russel and Corwin","bs":"bleeding-edge leverage infrastructures"},"80":{"id":80,"name":"Conn - Jerde","bs":"end-to-end integrate synergies"},"81":{"id":81,"name":"Douglas, Zulauf and Stiedemann","bs":"mission-critical envisioneer users"},"82":{"id":82,"name":"Lueilwitz - Bartell","bs":"e-business drive vortals"},"83":{"id":83,"name":"Ebert, Jacobson and Lebsack","bs":"B2C whiteboard infrastructures"},"84":{"id":84,"name":"Wisozk - Morissette","bs":"wireless expedite e-commerce"},"85":{"id":85,"name":"Jast LLC","bs":"transparent exploit eyeballs"},"86":{"id":86,"name":"Hilll and Sons","bs":"visionary transition channels"},"87":{"id":87,"name":"Berge, Marquardt and Heathcote","bs":"world-class deploy action-items"},"88":{"id":88,"name":"Hoeger and Sons","bs":"innovative mesh ROI"},"89":{"id":89,"name":"Runolfsdottir, Runte and Satterfield","bs":"front-end iterate metrics"},"90":{"id":90,"name":"Kshlerin - Cole","bs":"global recontextualize web-readiness"},"91":{"id":91,"name":"Daniel Group","bs":"virtual integrate solutions"},"92":{"id":92,"name":"Mueller, Ratke and Block","bs":"global embrace experiences"},"93":{"id":93,"name":"Schmeler, Jast and Baumbach","bs":"viral innovate metrics"},"94":{"id":94,"name":"Crooks LLC","bs":"enterprise syndicate convergence"},"95":{"id":95,"name":"Stark Group","bs":"dynamic incentivize infomediaries"},"96":{"id":96,"name":"Schumm LLC","bs":"clicks-and-mortar drive experiences"},"97":{"id":97,"name":"Cole, Tremblay and Rosenbaum","bs":"plug-and-play harness technologies"},"98":{"id":98,"name":"Rosenbaum, Shields and Kling","bs":"24/365 reinvent infomediaries"},"99":{"id":99,"name":"Hudson and Sons","bs":"24/365 utilize bandwidth"}}